json_repair/__init__.py
json_repair/json_repair.py
jsam_json_repair-0.0.3.dist-info/LICENCE
jsam_json_repair-0.0.3.dist-info/METADATA
jsam_json_repair-0.0.3.dist-info/WHEEL
jsam_json_repair-0.0.3.dist-info/top_level.txt
jsam_json_repair-0.0.3.dist-info/RECORD
