Metadata-Version: 2.1
Name: jsam-json-repair
Version: 0.0.3
Summary: This is a Python package for repairing JSON string.
Home-page: https://github.com/changjam/jsam_json_repair
Download-URL: https://pypi.org/project/jsam_json_repair/
Author: Jam
Author-email: changjam60@gmail.com
License: MIT
Classifier: Programming Language :: Python :: 3.7
Classifier: Programming Language :: Python :: 3.8
Classifier: Programming Language :: Python :: 3.9
Classifier: Programming Language :: Python :: 3.10
Classifier: Programming Language :: Python :: 3.11
Requires-Python: >=3.7
License-File: LICENCE
